BinaryOptionsToolsV2/BinaryOptionsToolsV2.pyd
BinaryOptionsToolsV2/__init__.py
BinaryOptionsToolsV2/config.py
BinaryOptionsToolsV2/pocketoption/__init__.py
BinaryOptionsToolsV2/pocketoption/asyncronous.py
BinaryOptionsToolsV2/pocketoption/syncronous.py
BinaryOptionsToolsV2/tracing.py
BinaryOptionsToolsV2/validator.py
binaryoptionstoolsv2-0.2.1.dist-info/METADATA
binaryoptionstoolsv2-0.2.1.dist-info/WHEEL
binaryoptionstoolsv2-0.2.1.dist-info/licenses/LICENSE
binaryoptionstoolsv2-0.2.1.dist-info/RECORD
