Metadata-Version: 2.4
Name: binaryoptionstoolsv2
Version: 0.2.1
Classifier: Development Status :: 4 - Beta
Classifier: Intended Audience :: Developers
Classifier: License :: OSI Approved :: BSD License
Classifier: Operating System :: OS Independent
Classifier: Programming Language :: Python
Classifier: Programming Language :: Python :: 3
Classifier: Programming Language :: Python :: 3.8
Classifier: Programming Language :: Python :: 3.9
Classifier: Programming Language :: Python :: 3.10
Classifier: Programming Language :: Python :: 3.11
Classifier: Programming Language :: Python :: 3.12
Classifier: Programming Language :: Python :: Implementation :: CPython
Classifier: Programming Language :: Python :: Implementation :: PyPy
Classifier: Programming Language :: Rust
Classifier: Topic :: Office/Business :: Financial
Classifier: Topic :: Software Development :: Libraries :: Python Modules
License-File: LICENSE
Summary: Python bindings for binary-options-tools. High-performance library for PocketOption trading automation with async/sync support, real-time data streaming, and WebSocket API access.
Keywords: binary options,trading,pocketoption,finance,async
Home-Page: https://chipadevteam.github.io/BinaryOptionsTools-v2/
Author: ChipaDevTeam, Rick-29
License: BSD
Requires-Python: >=3.8
Project-URL: Homepage, https://chipadevteam.github.io/BinaryOptionsTools-v2/
Project-URL: Documentation, https://chipadevteam.github.io/BinaryOptionsTools-v2/python.html
Project-URL: Repository, https://github.com/ChipaDevTeam/BinaryOptionsTools-v2
Project-URL: Bug Reports, https://github.com/ChipaDevTeam/BinaryOptionsTools-v2/issues
Project-URL: Source Code, https://github.com/ChipaDevTeam/BinaryOptionsTools-v2
Project-URL: Discord, https://discord.com/invite/chipa-1261483112991555665
